{
    "Menu": [
        {
            "id": "1",
            "name": "Coffee",
            "price": "20000",
            "img": "https://i.ibb.co/rc7vJ4k/Coffee.jpg"
        },
        {
            "id": "2",
            "name": "Soda",
            "price": "30000",
            "img": "https://i.ibb.co/pjnXwx6/Soda.jpg"
        },
        {
            "id": "3",
            "name": "Milk tea",
            "price": "25000",
            "img": "https://i.ibb.co/2NV314V/Milktea.webp"
        },
        {
            "id": "4",
            "name": "Lemonade",
            "price": "15000",
            "img": "https://i.ibb.co/yh9vdHj/Lemonade.jpg"
        },
        {
            "id": "5",
            "name": "Yogurt",
            "price": "30000",
            "img": "https://i.ibb.co/gttN0CV/Yogurt.jpg"
        },
        {
            "id": "6",
            "name": "Cocktail",
            "price": "60000",
            "img": "https://i.ibb.co/PTZgK02/Cocktail.jpg"
        },
        {
            "id": "7",
            "name": "Beer",
            "price": "30000",
            "img": "https://i.ibb.co/1LKdrDq/Beer.jpg"
        }
    ]
    
}
